[{"author": "duduujjjqoepf", "body": "what does that mean I dont understand (im being genuine)", "created_utc": "1667000371.0", "edited": "False", "id": "iu6pyaa", "is_submitter": "False", "link_id": "t3_yfmvcs", "parent_id": "t3_yfmvcs", "score": "1", "subreddit": "linguisticshumor", "subreddit_id": "t5_2vwiq"}, {"author": "duduujjjqoepf", "body": "uni\u00e3o europeia e Par\u00e1", "created_utc": "1665414264.0", "edited": "False", "id": "irroaae", "is_submitter": "False", "link_id": "t3_y0blv9", "parent_id": "t1_irqwg59", "score": "2", "subreddit": "flanelagameplays", "subreddit_id": "t5_6pi9bh"}, {"author": "duduujjjqoepf", "body": "Kim kataguiri vergonha nacional", "created_utc": "1664414550.0", "edited": "False", "id": "iqb9nv8", "is_submitter": "False", "link_id": "t3_xqsub9", "parent_id": "t3_xqsub9", "score": "14", "subreddit": "2latinoforyou", "subreddit_id": "t5_5d6c1s"}, {"author": "duduujjjqoepf", "body": "edo", "created_utc": "1664312382.0", "edited": "False", "id": "iq5k80z", "is_submitter": "False", "link_id": "t3_xpik2u", "parent_id": "t3_xpik2u", "score": "1", "subreddit": "tumblr", "subreddit_id": "t5_2r7hk"}, {"author": "duduujjjqoepf", "body": "Oi, MS", "created_utc": "1664145717.0", "edited": "False", "id": "ipwf99z", "is_submitter": "False", "link_id": "t3_xnx2mp", "parent_id": "t3_xnx2mp", "score": "2", "subreddit": "flanelagameplays", "subreddit_id": "t5_6pi9bh"}, {"author": "duduujjjqoepf", "body": "true", "created_utc": "1664125972.0", "edited": "False", "id": "ipv0gpy", "is_submitter": "False", "link_id": "t3_xnmim6", "parent_id": "t1_ipuqlc5", "score": "1", "subreddit": "imaginarymaps", "subreddit_id": "t5_2vqof"}, {"author": "duduujjjqoepf", "body": "yeah but there are some towns in the southern part of Brazil where it is the most spoken language", "created_utc": "1664121846.0", "edited": "False", "id": "ipuqcob", "is_submitter": "False", "link_id": "t3_xnmim6", "parent_id": "t1_ipulcoo", "score": "1", "subreddit": "imaginarymaps", "subreddit_id": "t5_2vqof"}, {"author": "duduujjjqoepf", "body": "German is the 2nd most spoken language in Brazil", "created_utc": "1664116929.0", "edited": "False", "id": "ipuex0t", "is_submitter": "False", "link_id": "t3_xnmim6", "parent_id": "t3_xnmim6", "score": "3", "subreddit": "imaginarymaps", "subreddit_id": "t5_2vqof"}, {"author": "duduujjjqoepf", "body": "MS? quando isso?", "created_utc": "1664116800.0", "edited": "False", "id": "ipuemig", "is_submitter": "False", "link_id": "t3_xn1uux", "parent_id": "t3_xn1uux", "score": "2", "subreddit": "flanelagameplays", "subreddit_id": "t5_6pi9bh"}, {"author": "duduujjjqoepf", "body": "Haiti + reino unido", "created_utc": "1663968715.0", "edited": "False", "id": "ipn7d2b", "is_submitter": "False", "link_id": "t3_xm0e8x", "parent_id": "t3_xm0e8x", "score": "1", "subreddit": "flanelagameplays", "subreddit_id": "t5_6pi9bh"}, {"author": "duduujjjqoepf", "body": "mto goo do u", "created_utc": "1663968554.0", "edited": "False", "id": "ipn70fw", "is_submitter": "False", "link_id": "t3_xm0v81", "parent_id": "t3_xm0v81", "score": "2", "subreddit": "flanelagameplays", "subreddit_id": "t5_6pi9bh"}, {"author": "duduujjjqoepf", "body": "Aqui em campo grande tem em todo lugar.", "created_utc": "1663877113.0", "edited": "False", "id": "ipihxg6", "is_submitter": "False", "link_id": "t3_xkhv4j", "parent_id": "t3_xkhv4j", "score": "2", "subreddit": "2latinoforyou", "subreddit_id": "t5_5d6c1s"}, {"author": "duduujjjqoepf", "body": "typa girl on my cock", "created_utc": "1663800010.0", "edited": "False", "id": "ipe7jiu", "is_submitter": "False", "link_id": "t3_xkgm8w", "parent_id": "t3_xkgm8w", "score": "1", "subreddit": "cursedcomments", "subreddit_id": "t5_hw1ju"}, {"author": "duduujjjqoepf", "body": "parece a de cg", "created_utc": "1663764072.0", "edited": "False", "id": "ipbnr63", "is_submitter": "False", "link_id": "t3_xjmnhp", "parent_id": "t3_xjmnhp", "score": "3", "subreddit": "flanelagameplays", "subreddit_id": "t5_6pi9bh"}, {"author": "duduujjjqoepf", "body": "buzz needs more \ud83d\ude14", "created_utc": "1663350102.0", "edited": "False", "id": "iooy6uj", "is_submitter": "False", "link_id": "t3_xfs244", "parent_id": "t3_xfs244", "score": "0", "subreddit": "Brawlstars", "subreddit_id": "t5_3k7ez"}, {"author": "duduujjjqoepf", "body": "u just down bad", "created_utc": "1663349343.0", "edited": "False", "id": "ioow82q", "is_submitter": "False", "link_id": "t3_xf9ddh", "parent_id": "t3_xf9ddh", "score": "1", "subreddit": "CoachCorySubmissions", "subreddit_id": "t5_10e2b7"}, {"author": "duduujjjqoepf", "body": "russian for sure", "created_utc": "1662740053.0", "edited": "False", "id": "inqr2i6", "is_submitter": "False", "link_id": "t3_x9pngp", "parent_id": "t3_x9pngp", "score": "5", "subreddit": "languagelearning", "subreddit_id": "t5_2rjsc"}, {"author": "duduujjjqoepf", "body": "Brasil", "created_utc": "1658698792.0", "edited": "False", "id": "ihhzbpj", "is_submitter": "False", "link_id": "t3_w6otu8", "parent_id": "t3_w6otu8", "score": "2", "subreddit": "flanelagameplays", "subreddit_id": "t5_6pi9bh"}, {"author": "duduujjjqoepf", "body": "so jacky needs a buff...", "created_utc": "1629109073.0", "edited": "False", "id": "h951kpy", "is_submitter": "False", "link_id": "t3_p53vx3", "parent_id": "t1_h9449ev", "score": "4", "subreddit": "CoachCorySubmissions", "subreddit_id": "t5_10e2b7"}, {"author": "duduujjjqoepf", "body": "do you are have stupid", "created_utc": "1625406389.0", "edited": "False", "id": "h40thjs", "is_submitter": "False", "link_id": "t3_odhrko", "parent_id": "t3_odhrko", "score": "6", "subreddit": "CoachCorySubmissions", "subreddit_id": "t5_10e2b7"}, {"author": "duduujjjqoepf", "body": "ewiz laugh asserts dominance", "created_utc": "1625405569.0", "edited": "False", "id": "h40s3dc", "is_submitter": "False", "link_id": "t3_odh9of", "parent_id": "t1_h40rtdl", "score": "2", "subreddit": "ClashRoyale", "subreddit_id": "t5_3bog8"}, {"author": "duduujjjqoepf", "body": "u/RepostSleuthBot", "created_utc": "1625401239.0", "edited": "False", "id": "h40lm6d", "is_submitter": "False", "link_id": "t3_oddt6a", "parent_id": "t3_oddt6a", "score": "1", "subreddit": "Brawlstars", "subreddit_id": "t5_3k7ez"}, {"author": "duduujjjqoepf", "body": "tick is my favorite brawler but this was funny i wasnt expecting that lmao", "created_utc": "1625400943.0", "edited": "False", "id": "h40l8yj", "is_submitter": "False", "link_id": "t3_od48tv", "parent_id": "t3_od48tv", "score": "2", "subreddit": "shittybrawlstars", "subreddit_id": "t5_12v71x"}, {"author": "duduujjjqoepf", "body": "sex.", "created_utc": "1625400842.0", "edited": "False", "id": "h40l4ii", "is_submitter": "False", "link_id": "t3_oddvln", "parent_id": "t1_h40ku4b", "score": "2", "subreddit": "CoachCorySubmissions", "subreddit_id": "t5_10e2b7"}, {"author": "duduujjjqoepf", "body": "u/RepostSleuthBot", "created_utc": "1624068084.0", "edited": "False", "id": "h2a2szd", "is_submitter": "False", "link_id": "t3_o2i9ym", "parent_id": "t3_o2i9ym", "score": "1", "subreddit": "CoachCorySubmissions", "subreddit_id": "t5_10e2b7"}, {"author": "duduujjjqoepf", "body": "Dani vem de Daniel", "created_utc": "1623551218.0", "edited": "False", "id": "h1kw4wk", "is_submitter": "False", "link_id": "t3_nyaec6", "parent_id": "t1_h1jec01", "score": "2", "subreddit": "Brawlstars", "subreddit_id": "t5_3k7ez"}, {"author": "duduujjjqoepf", "body": "u/RepostSleuthBot", "created_utc": "1621793409.0", "edited": "False", "id": "gz6p7qg", "is_submitter": "False", "link_id": "t3_nj5crm", "parent_id": "t3_nj5crm", "score": "4", "subreddit": "Brawlstars", "subreddit_id": "t5_3k7ez"}, {"author": "duduujjjqoepf", "body": "stop simping for a fckin creepy stalker that wants to fuck a cactus", "created_utc": "1621792963.0", "edited": "False", "id": "gz6o9qu", "is_submitter": "False", "link_id": "t3_n29sxo", "parent_id": "t3_n29sxo", "score": "0", "subreddit": "ColetteSimps", "subreddit_id": "t5_33t8zu"}, {"author": "duduujjjqoepf", "body": "no", "created_utc": "1620839996.0", "edited": "False", "id": "gxvjuxk", "is_submitter": "False", "link_id": "t3_nan51t", "parent_id": "t1_gxvggky", "score": "4", "subreddit": "Brawlstars", "subreddit_id": "t5_3k7ez"}, {"author": "duduujjjqoepf", "body": "u/savevideo", "created_utc": "1620839049.0", "edited": "False", "id": "gxvhjtq", "is_submitter": "False", "link_id": "t3_n5vgfh", "parent_id": "t3_n5vgfh", "score": "1", "subreddit": "OkBrawlerRetard", "subreddit_id": "t5_2498ln"}, {"author": "duduujjjqoepf", "body": "sanstastic \ud83d\ude33\ud83d\ude33 sus!!1", "created_utc": "1620839008.0", "edited": "False", "id": "gxvhg4m", "is_submitter": "False", "link_id": "t3_naojfr", "parent_id": "t3_naojfr", "score": "6", "subreddit": "shittybrawlstars", "subreddit_id": "t5_12v71x"}, {"author": "duduujjjqoepf", "body": "ohh thanks", "created_utc": "1620828751.0", "edited": "False", "id": "gxust28", "is_submitter": "False", "link_id": "t3_n9mrjy", "parent_id": "t1_gxsmgy6", "score": "1", "subreddit": "shittybrawlstars", "subreddit_id": "t5_12v71x"}, {"author": "duduujjjqoepf", "body": "source", "created_utc": "1620745003.0", "edited": "False", "id": "gxqhvl8", "is_submitter": "False", "link_id": "t3_n9mrjy", "parent_id": "t1_gxped6a", "score": "3", "subreddit": "shittybrawlstars", "subreddit_id": "t5_12v71x"}, {"author": "duduujjjqoepf", "body": "I like to think Monster is just Boyfriend's imagination", "created_utc": "1620656916.0", "edited": "False", "id": "gxm0qgm", "is_submitter": "False", "link_id": "t3_n91z2x", "parent_id": "t1_gxlmykj", "score": "28", "subreddit": "FridayNightFunkin", "subreddit_id": "t5_38f3iy"}, {"author": "duduujjjqoepf", "body": "I was getting some powercubes, I went from 10th place to 3rd place, so eh.", "created_utc": "1620611090.0", "edited": "False", "id": "gxk808z", "is_submitter": "False", "link_id": "t3_n8iufj", "parent_id": "t1_gxk7wdv", "score": "4", "subreddit": "Brawlstars", "subreddit_id": "t5_3k7ez"}, {"author": "duduujjjqoepf", "body": "I literally just played emz on takedown like rn and I was killing the players instead of the boss...", "created_utc": "1620610964.0", "edited": "False", "id": "gxk7sbx", "is_submitter": "False", "link_id": "t3_n8iufj", "parent_id": "t1_gxk2bu7", "score": "1", "subreddit": "Brawlstars", "subreddit_id": "t5_3k7ez"}, {"author": "duduujjjqoepf", "body": "u/savevideo", "created_utc": "1620535079.0", "edited": "False", "id": "gxgru3a", "is_submitter": "False", "link_id": "t3_n7ud3u", "parent_id": "t3_n7ud3u", "score": "1", "subreddit": "FridayNightFunkin", "subreddit_id": "t5_38f3iy"}, {"author": "duduujjjqoepf", "body": "happy cake day", "created_utc": "1620443906.0", "edited": "False", "id": "gxcmuoy", "is_submitter": "False", "link_id": "t3_n7c6ts", "parent_id": "t1_gxc7oys", "score": "20", "subreddit": "cursedcursedcomments", "subreddit_id": "t5_tdhql"}, {"author": "duduujjjqoepf", "body": "mine was penny(s) tho", "created_utc": "1620417452.0", "edited": "False", "id": "gxb8d9g", "is_submitter": "False", "link_id": "t3_mtmyjn", "parent_id": "t3_mtmyjn", "score": "2", "subreddit": "OkBrawlerRetard", "subreddit_id": "t5_2498ln"}, {"author": "duduujjjqoepf", "body": "which one is better for Prince", "created_utc": "1620417095.0", "edited": "False", "id": "gxb7mbz", "is_submitter": "False", "link_id": "t3_n71frr", "parent_id": "t3_n71frr", "score": "1", "subreddit": "ClashQuest", "subreddit_id": "t5_3i31f"}, {"author": "duduujjjqoepf", "body": "Lmaoooo. U r so funni haha", "created_utc": "1620415643.0", "edited": "False", "id": "gxb4h7d", "is_submitter": "False", "link_id": "t3_n6thhs", "parent_id": "t3_n6thhs", "score": "1", "subreddit": "JuicyNewsNetwork", "subreddit_id": "t5_3p7xwg"}, {"author": "duduujjjqoepf", "body": "you are going to  brazil", "created_utc": "1620415558.0", "edited": "False", "id": "gxb4aiz", "is_submitter": "False", "link_id": "t3_n6x2de", "parent_id": "t3_n6x2de", "score": "3", "subreddit": "OkBrawlerRetard", "subreddit_id": "t5_2498ln"}, {"author": "duduujjjqoepf", "body": "racism\nracism", "created_utc": "1620415335.0", "edited": "False", "id": "gxb3t6l", "is_submitter": "False", "link_id": "t3_n6yobx", "parent_id": "t3_n6yobx", "score": "1", "subreddit": "Brawlstars", "subreddit_id": "t5_3k7ez"}, {"author": "duduujjjqoepf", "body": "oh my bad, thx", "created_utc": "1620398379.0", "edited": "False", "id": "gxa0yo7", "is_submitter": "False", "link_id": "t3_n63sje", "parent_id": "t1_gx5wja2", "score": "2", "subreddit": "ClashQuest", "subreddit_id": "t5_3i31f"}, {"author": "duduujjjqoepf", "body": "I already did bruh...", "created_utc": "1620397801.0", "edited": "False", "id": "gx9zncy", "is_submitter": "False", "link_id": "t3_n5gcla", "parent_id": "t1_gx6deky", "score": "1", "subreddit": "CoachCorySubmissions", "subreddit_id": "t5_10e2b7"}, {"author": "duduujjjqoepf", "body": "I wonder what the opening says", "created_utc": "1620315709.0", "edited": "False", "id": "gx5tu79", "is_submitter": "False", "link_id": "t3_n65e8z", "parent_id": "t3_n65e8z", "score": "1", "subreddit": "ClashRoyale", "subreddit_id": "t5_3bog8"}, {"author": "duduujjjqoepf", "body": "will you continue to ignore me? \ud83d\ude02", "created_utc": "1620314825.0", "edited": "False", "id": "gx5rr2i", "is_submitter": "False", "link_id": "t3_n5gcla", "parent_id": "t1_gx1n9mx", "score": "1", "subreddit": "CoachCorySubmissions", "subreddit_id": "t5_10e2b7"}, {"author": "duduujjjqoepf", "body": "its 84, I saw on twitter", "created_utc": "1620314780.0", "edited": "False", "id": "gx5rnd7", "is_submitter": "False", "link_id": "t3_n63sje", "parent_id": "t1_gx5htgp", "score": "1", "subreddit": "ClashQuest", "subreddit_id": "t5_3i31f"}, {"author": "duduujjjqoepf", "body": "thx", "created_utc": "1620233729.0", "edited": "False", "id": "gx1oc32", "is_submitter": "False", "link_id": "t3_n5geyp", "parent_id": "t1_gx1oalx", "score": "1", "subreddit": "ClashQuest", "subreddit_id": "t5_3i31f"}, {"author": "duduujjjqoepf", "body": "how do i get Bomber", "created_utc": "1620233421.0", "edited": "False", "id": "gx1nk8u", "is_submitter": "False", "link_id": "t3_n5geyp", "parent_id": "t3_n5geyp", "score": "1", "subreddit": "ClashQuest", "subreddit_id": "t5_3i31f"}, {"author": "duduujjjqoepf", "body": "proofs that you are bamboozo", "created_utc": "1620233306.0", "edited": "False", "id": "gx1n9mx", "is_submitter": "False", "link_id": "t3_n5gcla", "parent_id": "t3_n5gcla", "score": "8", "subreddit": "CoachCorySubmissions", "subreddit_id": "t5_10e2b7"}, {"author": "duduujjjqoepf", "body": "ok", "created_utc": "1620150383.0", "edited": "False", "id": "gwxlhv9", "is_submitter": "False", "link_id": "t3_n4hq2t", "parent_id": "t1_gwxk8j2", "score": "1", "subreddit": "CoachCorySubmissions", "subreddit_id": "t5_10e2b7"}, {"author": "duduujjjqoepf", "body": "secs", "created_utc": "1620149948.0", "edited": "False", "id": "gwxkhlu", "is_submitter": "False", "link_id": "t3_n4l6ss", "parent_id": "t1_gwxa6ha", "score": "1", "subreddit": "shittybrawlstars", "subreddit_id": "t5_12v71x"}, {"author": "duduujjjqoepf", "body": "u/RepostSleuthBot", "created_utc": "1620149815.0", "edited": "False", "id": "gwxk6mh", "is_submitter": "False", "link_id": "t3_n4hq2t", "parent_id": "t3_n4hq2t", "score": "1", "subreddit": "CoachCorySubmissions", "subreddit_id": "t5_10e2b7"}, {"author": "duduujjjqoepf", "body": "I just found out that incest is not illegal in my country. huh", "created_utc": "1620149725.0", "edited": "False", "id": "gwxjyyb", "is_submitter": "False", "link_id": "t3_n3olip", "parent_id": "t1_gwvou5j", "score": "1", "subreddit": "Brawlstars", "subreddit_id": "t5_3k7ez"}, {"author": "duduujjjqoepf", "body": "is it illegal?", "created_utc": "1620072318.0", "edited": "False", "id": "gwtnbsr", "is_submitter": "False", "link_id": "t3_n3olip", "parent_id": "t1_gwt8mvx", "score": "1", "subreddit": "Brawlstars", "subreddit_id": "t5_3k7ez"}, {"author": "duduujjjqoepf", "body": "u/RepostSleuthBot", "created_utc": "1620072231.0", "edited": "False", "id": "gwtn4o5", "is_submitter": "False", "link_id": "t3_n3pf65", "parent_id": "t3_n3pf65", "score": "-1", "subreddit": "Brawlstars", "subreddit_id": "t5_3k7ez"}, {"author": "duduujjjqoepf", "body": "y'know, if you're playing solo power league you are also a random", "created_utc": "1620072078.0", "edited": "False", "id": "gwtms58", "is_submitter": "False", "link_id": "t3_n40jhu", "parent_id": "t3_n40jhu", "score": "5", "subreddit": "CoachCorySubmissions", "subreddit_id": "t5_10e2b7"}, {"author": "duduujjjqoepf", "body": "sharing their opinion", "created_utc": "1620017480.0", "edited": "False", "id": "gwqycz6", "is_submitter": "False", "link_id": "t3_n3cru1", "parent_id": "t1_gwqa5tt", "score": "2", "subreddit": "CoachCorySubmissions", "subreddit_id": "t5_10e2b7"}, {"author": "duduujjjqoepf", "body": "yep they can, but enemy team cant see the green circle if its gene's 1st sp", "created_utc": "1620017325.0", "edited": "False", "id": "gwqy5j6", "is_submitter": "False", "link_id": "t3_n366ip", "parent_id": "t3_n366ip", "score": "1", "subreddit": "brawlpoll", "subreddit_id": "t5_2nn19m"}, {"author": "duduujjjqoepf", "body": "man, this song is so familiar yet so strange", "created_utc": "1619985855.0", "edited": "False", "id": "gwpd1m5", "is_submitter": "False", "link_id": "t3_n34v2q", "parent_id": "t3_n34v2q", "score": "2", "subreddit": "FridayNightFunkin", "subreddit_id": "t5_38f3iy"}, {"author": "duduujjjqoepf", "body": "i didnt get it", "created_utc": "1619985442.0", "edited": "False", "id": "gwpc78j", "is_submitter": "False", "link_id": "t3_n39tnq", "parent_id": "t3_n39tnq", "score": "2", "subreddit": "cursedcomments", "subreddit_id": "t5_hw1ju"}, {"author": "duduujjjqoepf", "body": "U DUMB BENTIMMONE IS NO FREE TO PLAYER \ud83d\ude21\ud83d\ude21\ud83d\ude21\ud83d\ude20", "created_utc": "1619897914.0", "edited": "False", "id": "gwksa2k", "is_submitter": "False", "link_id": "t3_n2obun", "parent_id": "t3_n2obun", "score": "2", "subreddit": "OkBrawlerRetard", "subreddit_id": "t5_2498ln"}, {"author": "duduujjjqoepf", "body": "do mecha crow", "created_utc": "1619876340.0", "edited": "False", "id": "gwjf0e9", "is_submitter": "False", "link_id": "t3_n2c6hi", "parent_id": "t3_n2c6hi", "score": "1", "subreddit": "CoachCorySubmissions", "subreddit_id": "t5_10e2b7"}, {"author": "duduujjjqoepf", "body": "why?", "created_utc": "1619876320.0", "edited": "False", "id": "gwjez6c", "is_submitter": "False", "link_id": "t3_n2c6hi", "parent_id": "t1_gwiphut", "score": "1", "subreddit": "CoachCorySubmissions", "subreddit_id": "t5_10e2b7"}, {"author": "duduujjjqoepf", "body": "u/repostsleuthbot", "created_utc": "1619832479.0", "edited": "False", "id": "gwhtf3h", "is_submitter": "False", "link_id": "t3_n1lbvj", "parent_id": "t3_n1lbvj", "score": "1", "subreddit": "Brawlstars", "subreddit_id": "t5_3k7ez"}, {"author": "duduujjjqoepf", "body": "tara's bazaar because it was near my birthday", "created_utc": "1619811360.0", "edited": "False", "id": "gwgms76", "is_submitter": "False", "link_id": "t3_n1ob3h", "parent_id": "t3_n1ob3h", "score": "1", "subreddit": "brawlpoll", "subreddit_id": "t5_2nn19m"}, {"author": "duduujjjqoepf", "body": "Lou because\n\"I got the drip to make you slip\"", "created_utc": "1619811314.0", "edited": "False", "id": "gwgmoq7", "is_submitter": "False", "link_id": "t3_n1sa8k", "parent_id": "t3_n1sa8k", "score": "3", "subreddit": "brawlpoll", "subreddit_id": "t5_2nn19m"}, {"author": "duduujjjqoepf", "body": "science?", "created_utc": "1619810522.0", "edited": "False", "id": "gwgl02f", "is_submitter": "False", "link_id": "t3_n1rjbv", "parent_id": "t3_n1rjbv", "score": "1", "subreddit": "shittybrawlstars", "subreddit_id": "t5_12v71x"}, {"author": "duduujjjqoepf", "body": "i love when my mom do bdsm with me", "created_utc": "1619809760.0", "edited": "False", "id": "gwgjcos", "is_submitter": "False", "link_id": "t3_n1v8ju", "parent_id": "t3_n1v8ju", "score": "5", "subreddit": "terriblefacebookmemes", "subreddit_id": "t5_2tja6"}, {"author": "duduujjjqoepf", "body": "oooohhh his balls \ud83e\udd24\ud83e\udd24", "created_utc": "1619807482.0", "edited": "False", "id": "gwgeb4u", "is_submitter": "False", "link_id": "t3_n1nb9q", "parent_id": "t1_gwegj5l", "score": "1", "subreddit": "Brawlstars", "subreddit_id": "t5_3k7ez"}, {"author": "duduujjjqoepf", "body": "k", "created_utc": "1619806583.0", "edited": "False", "id": "gwgca6e", "is_submitter": "False", "link_id": "t3_n1nffd", "parent_id": "t1_gwgc7vp", "score": "1", "subreddit": "CoachCorySubmissions", "subreddit_id": "t5_10e2b7"}, {"author": "duduujjjqoepf", "body": "weeb", "created_utc": "1619806492.0", "edited": "False", "id": "gwgc2ud", "is_submitter": "False", "link_id": "t3_n1nffd", "parent_id": "t1_gwf0v1y", "score": "1", "subreddit": "CoachCorySubmissions", "subreddit_id": "t5_10e2b7"}, {"author": "duduujjjqoepf", "body": "spicy mike my beloved \u2665\ufe0f", "created_utc": "1619806371.0", "edited": "False", "id": "gwgbsxo", "is_submitter": "False", "link_id": "t3_n1lu4d", "parent_id": "t3_n1lu4d", "score": "1", "subreddit": "CoachCorySubmissions", "subreddit_id": "t5_10e2b7"}, {"author": "duduujjjqoepf", "body": "uh oh", "created_utc": "1619805255.0", "edited": "False", "id": "gwg992z", "is_submitter": "False", "link_id": "t3_n1uc10", "parent_id": "t1_gwfj74h", "score": "1", "subreddit": "CoachCorySubmissions", "subreddit_id": "t5_10e2b7"}, {"author": "duduujjjqoepf", "body": "i am will updoot my friend \ud83d\udc4d\ud83d\udc4d", "created_utc": "1619752095.0", "edited": "False", "id": "gwdr5aq", "is_submitter": "True", "link_id": "t3_n1iz2r", "parent_id": "t1_gwdr1pq", "score": "6", "subreddit": "shittybrawlstars", "subreddit_id": "t5_12v71x"}, {"author": "duduujjjqoepf", "body": "you forgot to censor the name", "created_utc": "1619751729.0", "edited": "False", "id": "gwdqfxp", "is_submitter": "False", "link_id": "t3_n1km5f", "parent_id": "t3_n1km5f", "score": "1", "subreddit": "shittybrawlstars", "subreddit_id": "t5_12v71x"}, {"author": "duduujjjqoepf", "body": "Leon probably said \"Mat\u00e9 a un Shelly con 10 cubos y ulti\" which translates to \"I killed a Shelly with 10 cubes and super\". only thing I could understand", "created_utc": "1619751707.0", "edited": "False", "id": "gwdqeez", "is_submitter": "False", "link_id": "t3_n1km5f", "parent_id": "t3_n1km5f", "score": "1", "subreddit": "shittybrawlstars", "subreddit_id": "t5_12v71x"}, {"author": "duduujjjqoepf", "body": "this isnt yours, you stole it from this post https://www.reddit.com/r/Brawlstars/comments/ggzmdj/rogue_mortis/?utm_medium=android_app&utm_source=share", "created_utc": "1619751492.0", "edited": "False", "id": "gwdpzt2", "is_submitter": "False", "link_id": "t3_n1jrqq", "parent_id": "t3_n1jrqq", "score": "5", "subreddit": "CoachCorySubmissions", "subreddit_id": "t5_10e2b7"}, {"author": "duduujjjqoepf", "body": "yeah", "created_utc": "1619745409.0", "edited": "False", "id": "gwdd32o", "is_submitter": "True", "link_id": "t3_n1iz2r", "parent_id": "t1_gwdcvac", "score": "6", "subreddit": "shittybrawlstars", "subreddit_id": "t5_12v71x"}, {"author": "duduujjjqoepf", "body": "k mb", "created_utc": "1619743827.0", "edited": "False", "id": "gwd9riw", "is_submitter": "False", "link_id": "t3_n12aen", "parent_id": "t1_gwbvtd8", "score": "1", "subreddit": "JuicyNewsNetwork", "subreddit_id": "t5_3p7xwg"}, {"author": "duduujjjqoepf", "body": "r slash coachcorysubmissions after they see the number 9", "created_utc": "1619711646.0", "edited": "False", "id": "gwb4zxw", "is_submitter": "False", "link_id": "t3_n0y0q7", "parent_id": "t3_n0y0q7", "score": "1", "subreddit": "CoachCorySubmissions", "subreddit_id": "t5_10e2b7"}, {"author": "duduujjjqoepf", "body": "aim your super in the middle then use gadget right after it", "created_utc": "1619711514.0", "edited": "False", "id": "gwb4ocw", "is_submitter": "False", "link_id": "t3_n12aen", "parent_id": "t1_gwacdoi", "score": "2", "subreddit": "JuicyNewsNetwork", "subreddit_id": "t5_3p7xwg"}, {"author": "duduujjjqoepf", "body": "cringe", "created_utc": "1619665368.0", "edited": "False", "id": "gw95he4", "is_submitter": "False", "link_id": "t3_n0ch13", "parent_id": "t3_n0ch13", "score": "1", "subreddit": "CoachCorySubmissions", "subreddit_id": "t5_10e2b7"}, {"author": "duduujjjqoepf", "body": "where funi", "created_utc": "1619665063.0", "edited": "False", "id": "gw94x7i", "is_submitter": "False", "link_id": "t3_n0aope", "parent_id": "t3_n0aope", "score": "1", "subreddit": "CoachCorySubmissions", "subreddit_id": "t5_10e2b7"}, {"author": "duduujjjqoepf", "body": "Kinda", "created_utc": "1619663994.0", "edited": "False", "id": "gw92wki", "is_submitter": "False", "link_id": "t3_n0ixp2", "parent_id": "t1_gw92w7x", "score": "2", "subreddit": "JuicyNewsNetwork", "subreddit_id": "t5_3p7xwg"}, {"author": "duduujjjqoepf", "body": "Ohh I can see it", "created_utc": "1619663989.0", "edited": "False", "id": "gw92w7x", "is_submitter": "False", "link_id": "t3_n0ixp2", "parent_id": "t3_n0ixp2", "score": "1", "subreddit": "JuicyNewsNetwork", "subreddit_id": "t5_3p7xwg"}, {"author": "duduujjjqoepf", "body": "Hi confusion, I'm Dad!", "created_utc": "1619663969.0", "edited": "False", "id": "gw92usg", "is_submitter": "False", "link_id": "t3_n0ixp2", "parent_id": "t1_gw7j93h", "score": "4", "subreddit": "JuicyNewsNetwork", "subreddit_id": "t5_3p7xwg"}, {"author": "duduujjjqoepf", "body": "nice!", "created_utc": "1619582130.0", "edited": "False", "id": "gw4v7de", "is_submitter": "False", "link_id": "t3_n05v38", "parent_id": "t3_n05v38", "score": "2", "subreddit": "CoachCorySubmissions", "subreddit_id": "t5_10e2b7"}, {"author": "duduujjjqoepf", "body": "relatable", "created_utc": "1619577056.0", "edited": "False", "id": "gw4mbqh", "is_submitter": "False", "link_id": "t3_mztfcy", "parent_id": "t1_gw3uuaw", "score": "6", "subreddit": "FridayNightFunkin", "subreddit_id": "t5_38f3iy"}, {"author": "duduujjjqoepf", "body": "insta downvote", "created_utc": "1619576216.0", "edited": "False", "id": "gw4kqt5", "is_submitter": "False", "link_id": "t3_mzpoli", "parent_id": "t3_mzpoli", "score": "3", "subreddit": "CoachCorySubmissions", "subreddit_id": "t5_10e2b7"}, {"author": "duduujjjqoepf", "body": "haha stealing memes go brr", "created_utc": "1619537629.0", "edited": "False", "id": "gw278iu", "is_submitter": "False", "link_id": "t3_mznprq", "parent_id": "t3_mznprq", "score": "17", "subreddit": "CoachCorySubmissions", "subreddit_id": "t5_10e2b7"}, {"author": "duduujjjqoepf", "body": "besides newgrounds games", "created_utc": "1619537326.0", "edited": "False", "id": "gw26iqb", "is_submitter": "False", "link_id": "t3_mzqw04", "parent_id": "t1_gw26heq", "score": "1", "subreddit": "FridayNightFunkin", "subreddit_id": "t5_38f3iy"}, {"author": "duduujjjqoepf", "body": "what is your favorite game ?", "created_utc": "1619537310.0", "edited": "False", "id": "gw26heq", "is_submitter": "False", "link_id": "t3_mzqw04", "parent_id": "t3_mzqw04", "score": "1", "subreddit": "FridayNightFunkin", "subreddit_id": "t5_38f3iy"}, {"author": "duduujjjqoepf", "body": "eheheh me hate edgar \ud83d\ude20\ud83d\ude20\ud83d\ude20\ud83d\ude21\ud83d\ude21\ud83d\ude21\ud83d\ude21\ud83d\ude21\ud83d\ude20\ud83d\ude21\ud83d\ude42\ud83d\ude36\ud83d\ude12\ud83e\udd17\ud83e\udd17\ud83e\udd17", "created_utc": "1619495038.0", "edited": "False", "id": "gw0gcet", "is_submitter": "False", "link_id": "t3_mzeqgw", "parent_id": "t3_mzeqgw", "score": "1", "subreddit": "CoachCorySubmissions", "subreddit_id": "t5_10e2b7"}, {"author": "duduujjjqoepf", "body": "r/shittybrawlstars", "created_utc": "1619494662.0", "edited": "False", "id": "gw0fql7", "is_submitter": "False", "link_id": "t3_mytmqx", "parent_id": "t3_mytmqx", "score": "2", "subreddit": "CoachCorySubmissions", "subreddit_id": "t5_10e2b7"}, {"author": "duduujjjqoepf", "body": "frick, mine is only rank 35\nalso congrats", "created_utc": "1619411411.0", "edited": "False", "id": "gvw9fgj", "is_submitter": "False", "link_id": "t3_mjwoz2", "parent_id": "t1_gvw98ea", "score": "1", "subreddit": "shittybrawlstars", "subreddit_id": "t5_12v71x"}, {"author": "duduujjjqoepf", "body": "Good bot", "created_utc": "1619411004.0", "edited": "False", "id": "gvw8ukj", "is_submitter": "False", "link_id": "t3_mfwtpo", "parent_id": "t1_gt0g1tf", "score": "1", "subreddit": "shittybrawlstars", "subreddit_id": "t5_12v71x"}, {"author": "duduujjjqoepf", "body": "stop complaining and get some free ez trophies then lmao", "created_utc": "1619410725.0", "edited": "False", "id": "gvw8fo1", "is_submitter": "False", "link_id": "t3_mjwoz2", "parent_id": "t1_gv5w7h6", "score": "1", "subreddit": "shittybrawlstars", "subreddit_id": "t5_12v71x"}, {"author": "duduujjjqoepf", "body": "the white hair match", "created_utc": "1619276460.0", "edited": "False", "id": "gvpmbru", "is_submitter": "False", "link_id": "t3_mx74xi", "parent_id": "t3_mx74xi", "score": "1", "subreddit": "JuicyNewsNetwork", "subreddit_id": "t5_3p7xwg"}, {"author": "duduujjjqoepf", "body": "looks like someone just broke the rule 3 :D", "created_utc": "1619150188.0", "edited": "False", "id": "gvj2erh", "is_submitter": "False", "link_id": "t3_mvybqy", "parent_id": "t3_mvybqy", "score": "1", "subreddit": "CoachCorySubmissions", "subreddit_id": "t5_10e2b7"}, {"author": "duduujjjqoepf", "body": "mortis underdog in knockout", "created_utc": "1619150053.0", "edited": "False", "id": "gvj26xc", "is_submitter": "False", "link_id": "t3_mw9ot3", "parent_id": "t1_gvgxxg4", "score": "1", "subreddit": "CoachCorySubmissions", "subreddit_id": "t5_10e2b7"}, {"author": "duduujjjqoepf", "body": "both", "created_utc": "1619149539.0", "edited": "False", "id": "gvj1buv", "is_submitter": "False", "link_id": "t3_mwiuhr", "parent_id": "t1_gvifob7", "score": "4", "subreddit": "CoachCorySubmissions", "subreddit_id": "t5_10e2b7"}, {"author": "duduujjjqoepf", "body": "does it really happen?", "created_utc": "1619149312.0", "edited": "False", "id": "gvj0y32", "is_submitter": "False", "link_id": "t3_mwbypw", "parent_id": "t3_mwbypw", "score": "1", "subreddit": "CoachCorySubmissions", "subreddit_id": "t5_10e2b7"}, {"author": "duduujjjqoepf", "body": "you actually can", "created_utc": "1617204629.0", "edited": "False", "id": "gsxa2vr", "is_submitter": "False", "link_id": "t3_mh5q98", "parent_id": "t3_mh5q98", "score": "1", "subreddit": "JuicyNewsNetwork", "subreddit_id": "t5_3p7xwg"}, {"author": "duduujjjqoepf", "body": "Y\nE\nS\n.", "created_utc": "1617204471.0", "edited": "False", "id": "gsx9qgr", "is_submitter": "False", "link_id": "t3_mh4pis", "parent_id": "t3_mh4pis", "score": "1", "subreddit": "CoachCorySubmissions", "subreddit_id": "t5_10e2b7"}]